narada_core/__init__.py
narada_core/errors.py
narada_core/models.py
narada_core/py.typed
narada_core/actions/__init__.py
narada_core/actions/models.py
narada_core-0.0.9.dist-info/METADATA
narada_core-0.0.9.dist-info/WHEEL
narada_core-0.0.9.dist-info/RECORD
