Metadata-Version: 2.4
Name: narada-core
Version: 0.0.9
Summary: Code shared by the `narada` and `narada-pyodide` packages.
Project-URL: Homepage, https://github.com/NaradaAI/narada-python-sdk/narada-core
Project-URL: Repository, https://github.com/NaradaAI/narada-python-sdk
Project-URL: Issues, https://github.com/NaradaAI/narada-python-sdk/issues
Author-email: Narada <support@narada.ai>
License-Expression: Apache-2.0
Requires-Python: >=3.12
Requires-Dist: pydantic==2.10.6
